zentra/__init__.py
zentra/client.py
zentra/message.py
zentra-0.1.0.dist-info/LICENSE
zentra-0.1.0.dist-info/METADATA
zentra-0.1.0.dist-info/WHEEL
zentra-0.1.0.dist-info/top_level.txt
zentra-0.1.0.dist-info/RECORD
